MANIFEST.in
README.md
setup.cfg
setup.py
django_images_placeholder/__init__.py
django_images_placeholder/apps.py
django_images_placeholder/custom_storage.py
django_images_placeholder/tests.py
django_images_placeholder/urls.py
django_images_placeholder/utils.py
django_images_placeholder/views.py
django_images_placeholder.egg-info/PKG-INFO
django_images_placeholder.egg-info/SOURCES.txt
django_images_placeholder.egg-info/dependency_links.txt
django_images_placeholder.egg-info/top_level.txt