Metadata-Version: 1.1
Name: django-images-placeholder
Version: 0.0.5
Summary: Automatic generates images with the right dimensions whenit's missing from the local media storage based on a commondatabase or remote MEDIA_URL.
Home-page: https://bitbucket.org/3mwdigital/django-images-placeholder
Author: Joao Vitor Gomes [at] The Goodfellas
Author-email: joao.gomes@thegoodfellas.com.br
License: BSD 2
Platform: UNKNOWN
Classifier: Development Status :: 1 - Planning
Classifier: Environment :: Web Environment
Classifier: Framework :: Django
Classifier: Framework :: Django :: 1.9
Classifier: Framework :: Django :: 1.10
Classifier: Framework :: Django :: 1.11
Classifier: Intended Audience :: Developers
Classifier: License :: OSI Approved :: BSD License
Classifier: Operating System :: OS Independent
Classifier: Programming Language :: Python
Classifier: Programming Language :: Python :: 2
Classifier: Programming Language :: Python :: 2.7
Classifier: Programming Language :: Python :: 3
Classifier: Programming Language :: Python :: 3.3
Classifier: Programming Language :: Python :: 3.4
Classifier: Programming Language :: Python :: 3.5
Classifier: Programming Language :: Python :: 3.6
Classifier: Topic :: Software Development :: Libraries :: Python Modules
